{
  "filter-tag": {
    "rested": {
      "text-color": {
        "value": "#A1A1A1",
        "type": "color"
      },
      "border-color": {
        "value": "#e1e1e1",
        "type": "color"
      },
      "background-color": {
        "value": "#FCFCFC",
        "type": "color"
      }
    },
    "hover": {
      "text-color": {
        "value": "#454545",
        "type": "color"
      },
      "border-color": {
        "value": "#e1e1e1",
        "type": "color"
      },
      "background-color": {
        "value": "#fcfcfc",
        "type": "color"
      }
    },
    "active": {
      "text-color": {
        "value": "#000000",
        "type": "color"
      },
      "border-color": {
        "value": "#e1e1e1",
        "type": "color"
      },
      "background-color": {
        "value": "#fcfcfc",
        "type": "color"
      }
    },
    "disabled": {
      "text-color": {
        "value": "#B7B7B7",
        "type": "color"
      },
      "border-color": {
        "value": "#e2e2e2",
        "type": "color"
      },
      "background-color": {
        "value": "#eaeaea",
        "type": "color"
      }
    },
    "border-width": {
      "value": "{border-width.xs}",
      "type": "borderWidth"
    }
  },
  "filter tags": {
    "text": {
      "typography": {
        "value": "{general.global.XS-1-default}",
        "type": "typography"
      }
    }
  },
  "filtertag": {
    "height": {
      "value": "{dimension.500}",
      "type": "sizing"
    },
    "width": {
      "value": "{dimension.500}",
      "type": "sizing"
    },
    "padding-horizontal": {
      "value": "{dimension.150}",
      "type": "spacing"
    }
  }
}