{
  "list": {
    "item": {
      "default": {
        "text-typography": {
          "value": "{general.global.S-1-default}",
          "type": "typography"
        }
      },
      "hover": {
        "text-typography": {
          "value": "{general.global.S-1-link}",
          "type": "typography"
        }
      }
    },
    "title": {
      "text-color": {
        "value": "{semantic.color.typography.list.title-color}",
        "type": "color"
      },
      "text-typography": {
        "value": "{general.global.XXS-2-emphasis}",
        "type": "typography"
      }
    },
    "active": {
      "text-color": {
        "value": "{semantic.color.typography.list.active.text-color}",
        "type": "color"
      }
    },
    "rested": {
      "text-color": {
        "value": "{semantic.color.typography.list.rested.text-color}",
        "type": "color"
      }
    },
    "gap": {
      "value": "16",
      "type": "spacing"
    }
  }
}