{
  "qtyselector": {
    "border-radius": {
      "value": "{border-radius.sm}",
      "type": "borderRadius"
    }
  },
  "sm": {
    "padding-right": {
      "value": "{semantic.spacing.actions.sm.padding-right}",
      "type": "spacing"
    },
    "padding-left": {
      "value": "{semantic.spacing.actions.sm.padding-left}",
      "type": "spacing"
    },
    "padding-top": {
      "value": "{semantic.spacing.actions.sm.padding-top}",
      "type": "spacing"
    },
    "padding-bottom": {
      "value": "{semantic.spacing.actions.sm.padding-bottom}",
      "type": "spacing"
    }
  },
  "sizeselector": {
    "typography": {
      "value": "{semantic.typography.text.md.default}",
      "type": "typography"
    }
  },
  "md": {
    "padding-top": {
      "value": "{semantic.spacing.actions.md.padding-top}",
      "type": "spacing"
    },
    "padding-bottom": {
      "value": "{semantic.spacing.actions.md.padding-bottom}",
      "type": "spacing"
    }
  },
  "lg": {
    "padding-left": {
      "value": "{semantic.spacing.actions.lg.padding-left}",
      "type": "spacing"
    },
    "padding-right": {
      "value": "{semantic.spacing.actions.lg.padding-right}",
      "type": "spacing"
    }
  },
  "quantity counter": {
    "typography": {
      "value": "{semantic.typography.text.md.default}",
      "type": "typography"
    }
  },
  "qty-selector": {
    "size-selector": {
      "rested": {
        "fg-color": {
          "value": "{semantic.color.qty-selector.size-selector.rested.fg}",
          "type": "color"
        }
      },
      "hover": {
        "fg-color": {
          "value": "{semantic.color.qty-selector.size-selector.hover.fg}",
          "type": "color"
        },
        "bg-color": {
          "value": "{semantic.color.qty-selector.size-selector.hover.bg}",
          "type": "color"
        },
        "border-color": {
          "value": "{semantic.color.qty-selector.size-selector.hover.border}",
          "type": "color"
        }
      },
      "active": {
        "fg-color": {
          "value": "{semantic.color.qty-selector.size-selector.active.fg}",
          "type": "color"
        },
        "bg-color": {
          "value": "{semantic.color.qty-selector.size-selector.active.bg}",
          "type": "color"
        },
        "border-color": {
          "value": "{semantic.color.qty-selector.size-selector.active.border}",
          "type": "color"
        }
      }
    },
    "qty-button": {
      "neutral": {
        "rested": {
          "fg-color": {
            "value": "{semantic.color.qty-selector.qty-button.neutral.rested.fg}",
            "type": "color"
          },
          "border-color": {
            "value": "{semantic.color.qty-selector.qty-button.neutral.rested.border}",
            "type": "color"
          }
        },
        "hover": {
          "fg-color": {
            "value": "{semantic.color.qty-selector.qty-button.neutral.hover.fg}",
            "type": "color"
          },
          "bg-color": {
            "value": "{semantic.color.qty-selector.qty-button.neutral.hover.bg}",
            "type": "color"
          },
          "border-color": {
            "value": "{semantic.color.qty-selector.qty-button.neutral.hover.border}",
            "type": "color"
          }
        },
        "disabled": {
          "fg-color": {
            "value": "{semantic.color.qty-selector.qty-button.neutral.disabled.fg}",
            "type": "color"
          },
          "border-color": {
            "value": "{semantic.color.qty-selector.qty-button.neutral.disabled.border}",
            "type": "color"
          }
        }
      },
      "accent": {
        "rested": {
          "fg-color": {
            "value": "{semantic.color.qty-selector.qty-button.accent.rested.fg}",
            "type": "color"
          },
          "border-color": {
            "value": "{semantic.color.qty-selector.qty-button.accent.rested.border}",
            "type": "color"
          }
        },
        "hover": {
          "fg-color": {
            "value": "{semantic.color.qty-selector.qty-button.accent.hover.fg}",
            "type": "color"
          },
          "bg": {
            "value": "{semantic.color.surface.primary.default.bg}",
            "type": "color"
          },
          "border-color": {
            "value": "{semantic.color.surface.primary.default.border}",
            "type": "color"
          }
        },
        "disabled": {
          "fg-color": {
            "value": "{semantic.color.qty-selector.qty-button.accent.disabled.fg}",
            "type": "color"
          },
          "border-color": {
            "value": "{semantic.color.qty-selector.qty-button.accent.disabled.border}",
            "type": "color"
          }
        }
      },
      "inverse": {
        "rested": {
          "fg-color": {
            "value": "{semantic.color.qty-selector.qty-button.inverse.rested.fg}",
            "type": "color"
          },
          "border-color": {
            "value": "{semantic.color.qty-selector.qty-button.inverse.rested.border}",
            "type": "color"
          }
        },
        "hover": {
          "fg-color": {
            "value": "{semantic.color.qty-selector.qty-button.inverse.hover.fg}",
            "type": "color"
          },
          "bg-color": {
            "value": "{semantic.color.qty-selector.qty-button.inverse.hover.bg}",
            "type": "color"
          },
          "border-color": {
            "value": "{semantic.color.qty-selector.qty-button.inverse.hover.border}",
            "type": "color"
          }
        },
        "disabled": {
          "fg-color": {
            "value": "{semantic.color.qty-selector.qty-button.inverse.disabled.fg}",
            "type": "color"
          },
          "border-color": {
            "value": "{semantic.color.qty-selector.qty-button.inverse.disabled.border}",
            "type": "color"
          }
        }
      }
    },
    "qty-counter": {
      "neutral": {
        "rested": {
          "fg-color": {
            "value": "{semantic.color.qty-selector.qty-counter.neutral.rested.fg}",
            "type": "color"
          },
          "border-color": {
            "value": "{semantic.color.qty-selector.qty-counter.neutral.rested.border}",
            "type": "color"
          }
        },
        "hover": {
          "fg-color": {
            "value": "{semantic.color.qty-selector.qty-counter.neutral.hover.fg}",
            "type": "color"
          },
          "bg-color": {
            "value": "{semantic.color.qty-selector.qty-counter.neutral.hover.bg}",
            "type": "color"
          },
          "border-color": {
            "value": "{semantic.color.qty-selector.qty-counter.neutral.hover.border}",
            "type": "color"
          }
        },
        "active": {
          "fg-color": {
            "value": "{semantic.color.qty-selector.qty-counter.neutral.active.fg}",
            "type": "color"
          },
          "bg-color": {
            "value": "{semantic.color.qty-selector.qty-counter.neutral.active.bg}",
            "type": "color"
          },
          "border-color": {
            "value": "{semantic.color.qty-selector.qty-counter.neutral.active.border}",
            "type": "color"
          }
        },
        "disabled": {
          "fg-color": {
            "value": "{semantic.color.qty-selector.qty-counter.neutral.disabled.fg}",
            "type": "color"
          },
          "border-color": {
            "value": "{semantic.color.qty-selector.qty-counter.neutral.disabled.border}",
            "type": "color"
          }
        }
      },
      "error": {
        "fg-color": {
          "value": "{semantic.color.qty-selector.qty-counter.neutral.error.fg}",
          "type": "color"
        },
        "border-color": {
          "value": "{semantic.color.qty-selector.qty-counter.neutral.error.border}",
          "type": "color"
        }
      },
      "accent": {
        "rested": {
          "fg-color": {
            "value": "{semantic.color.qty-selector.qty-counter.accent.rested.fg}",
            "type": "color"
          },
          "border-color": {
            "value": "{semantic.color.qty-selector.qty-counter.accent.rested.border}",
            "type": "color"
          }
        },
        "hover": {
          "fg-color": {
            "value": "{semantic.color.qty-selector.qty-counter.accent.hover.fg}",
            "type": "color"
          },
          "bg-color": {
            "value": "{semantic.color.qty-selector.qty-counter.accent.hover.bg}",
            "type": "color"
          },
          "border-color": {
            "value": "{semantic.color.qty-selector.qty-counter.accent.hover.border}",
            "type": "color"
          }
        },
        "active": {
          "fg-color": {
            "value": "{semantic.color.qty-selector.qty-counter.accent.active.fg}",
            "type": "color"
          },
          "bg-color": {
            "value": "{semantic.color.qty-selector.qty-counter.accent.active.bg}",
            "type": "color"
          },
          "border-color": {
            "value": "{semantic.color.qty-selector.qty-counter.accent.active.border}",
            "type": "color"
          }
        },
        "disabled": {
          "fg-color": {
            "value": "{semantic.color.qty-selector.qty-counter.accent.disabled.fg}",
            "type": "color"
          },
          "border-color": {
            "value": "{semantic.color.qty-selector.qty-counter.accent.disabled.border}",
            "type": "color"
          }
        }
      },
      "inverted": {
        "rested": {
          "fg-color": {
            "value": "{semantic.color.qty-selector.qty-counter.inverse.rested.fg}",
            "type": "color"
          },
          "border-color": {
            "value": "{semantic.color.qty-selector.qty-counter.inverse.rested.border}",
            "type": "color"
          }
        },
        "hover": {
          "fg-color": {
            "value": "{semantic.color.qty-selector.qty-counter.inverse.hover.fg}",
            "type": "color"
          },
          "bg-color": {
            "value": "{semantic.color.qty-selector.qty-counter.inverse.hover.bg}",
            "type": "color"
          },
          "border-color": {
            "value": "{semantic.color.qty-selector.qty-counter.inverse.hover.border}",
            "type": "color"
          }
        },
        "active": {
          "fg-color": {
            "value": "{semantic.color.qty-selector.qty-counter.inverse.active.fg}",
            "type": "color"
          },
          "bg-color": {
            "value": "{semantic.color.qty-selector.qty-counter.inverse.active.bg}",
            "type": "color"
          },
          "border-color": {
            "value": "{semantic.color.qty-selector.qty-counter.inverse.active.border}",
            "type": "color"
          }
        },
        "disabled": {
          "fg-color": {
            "value": "{semantic.color.qty-selector.qty-counter.inverse.disabled.fg}",
            "type": "color"
          },
          "border-color": {
            "value": "{semantic.color.qty-selector.qty-counter.inverse.disabled.border}",
            "type": "color"
          }
        },
        "error": {
          "fg-color": {
            "value": "{semantic.color.qty-selector.qty-counter.inverse.error.fg}",
            "type": "color"
          },
          "border-color": {
            "value": "{semantic.color.qty-selector.qty-counter.inverse.error.border}",
            "type": "color"
          }
        }
      }
    }
  }
}